grrif_tools/__init__.py
grrif_tools/__main__.py
grrif_tools/cli.py
grrif_tools/grrif_archiver.py
grrif_tools/grrif_player.py
grrif_tools/grrif_scrobbler.py
grrif_tools/grrif_stats.py
grrif_tools/tui.py
grrif_tools/utils.py
grrif_tools/version.py
grrif_tools-0.9.1.dist-info/licenses/LICENSE
grrif_tools-0.9.1.dist-info/METADATA
grrif_tools-0.9.1.dist-info/WHEEL
grrif_tools-0.9.1.dist-info/top_level.txt
grrif_tools-0.9.1.dist-info/RECORD
