Metadata-Version: 2.4
Name: grrif_tools
Version: 0.9.1
Summary: An unofficial set of tools for Cool Cats™.
Home-page: https://github.com/fetzu/grrif-tools
Download-URL: https://github.com/fetzu/grrif-tools/releases/latest
Author: Julien 'fetzu' Bono
License: MIT License
Project-URL: Homepage, https://github.com/fetzu/grrif-tools
Project-URL: Bug Tracker, https://github.com/fetzu/grrif-tools/issues
Classifier: Programming Language :: Python :: 3
Classifier: License :: OSI Approved :: MIT License
Classifier: Operating System :: OS Independent
Requires-Python: >=3.9
License-File: LICENSE
Requires-Dist: requests>=2.30.0
Requires-Dist: beautifulsoup4>=4.12.0
Requires-Dist: titlecase>=2.4.0
Requires-Dist: miniaudio>=1.60
Requires-Dist: textual>=0.52.0
Dynamic: download-url
Dynamic: home-page
Dynamic: license-file
Dynamic: requires-python
